sequence_jacobian/__init__.py
sequence_jacobian/estimation.py
sequence_jacobian/grids.py
sequence_jacobian/interpolate.py
sequence_jacobian/misc.py
sequence_jacobian/blocks/__init__.py
sequence_jacobian/blocks/block.py
sequence_jacobian/blocks/combined_block.py
sequence_jacobian/blocks/het_block.py
sequence_jacobian/blocks/simple_block.py
sequence_jacobian/blocks/solved_block.py
sequence_jacobian/blocks/stage_block.py
sequence_jacobian/blocks/auxiliary_blocks/__init__.py
sequence_jacobian/blocks/auxiliary_blocks/jacobiandict_block.py
sequence_jacobian/blocks/support/__init__.py
sequence_jacobian/blocks/support/het_compiled.py
sequence_jacobian/blocks/support/het_support.py
sequence_jacobian/blocks/support/law_of_motion.py
sequence_jacobian/blocks/support/parent.py
sequence_jacobian/blocks/support/simple_displacement.py
sequence_jacobian/blocks/support/stages.py
sequence_jacobian/blocks/support/steady_state.py
sequence_jacobian/classes/__init__.py
sequence_jacobian/classes/impulse_dict.py
sequence_jacobian/classes/jacobian_dict.py
sequence_jacobian/classes/result_dict.py
sequence_jacobian/classes/sparse_jacobians.py
sequence_jacobian/classes/steady_state_dict.py
sequence_jacobian/examples/__init__.py
sequence_jacobian/examples/hank.py
sequence_jacobian/examples/krusell_smith.py
sequence_jacobian/examples/rbc.py
sequence_jacobian/examples/two_asset.py
sequence_jacobian/hetblocks/__init__.py
sequence_jacobian/hetblocks/hh_labor.py
sequence_jacobian/hetblocks/hh_sim.py
sequence_jacobian/hetblocks/hh_twoasset.py
sequence_jacobian/utilities/__init__.py
sequence_jacobian/utilities/bijection.py
sequence_jacobian/utilities/differentiate.py
sequence_jacobian/utilities/discretize.py
sequence_jacobian/utilities/drawdag.py
sequence_jacobian/utilities/function.py
sequence_jacobian/utilities/graph.py
sequence_jacobian/utilities/interpolate.py
sequence_jacobian/utilities/misc.py
sequence_jacobian/utilities/multidim.py
sequence_jacobian/utilities/optimized_routines.py
sequence_jacobian-1.0.0.dist-info/LICENSE
sequence_jacobian-1.0.0.dist-info/METADATA
sequence_jacobian-1.0.0.dist-info/WHEEL
sequence_jacobian-1.0.0.dist-info/top_level.txt
sequence_jacobian-1.0.0.dist-info/RECORD
