Metadata-Version: 2.1
Name: sequence-jacobian
Version: 1.0.0
Summary: Sequence-Space Jacobian Methods for Solving and Estimating Heterogeneous Agent Models
Home-page: https://github.com/shade-econ/sequence-jacobian
Author: Sequence-Jacobian Team
Author-email: sequence.jacobian.team@gmail.com
License: UNKNOWN
Project-URL: Bug Tracker, https://github.com/shade-econ/sequence-jacobian/issues
Platform: UNKNOWN
Classifier: Programming Language :: Python :: 3
Classifier: License :: OSI Approved :: MIT License
Classifier: Operating System :: OS Independent
Requires-Python: >=3.7
License-File: LICENSE
